{
  "data": "2025-05-20",
  "ora": "19:02:00",
  "negozio": "SUPERMERCATI MARTINELLI S.R.L.",
  "indirizzo": "V. COMMERCI0 1, 46030 S.G.MANTOVA MN",
  "città": "S.G.MANTOVA - MN",
  "paese": "Italia",
  "lista_articoli": [
    {
      "nome": "COLUSSI G.DISPENSA",
      "quantita": 1,
      "prezzo": 2.2,
      "valuta": "EUR",
      "percentuale_sconto": null,
      "sconto_assoluto": null,
      "valore_scontato": null
    },
    {
      "nome": "NATURELLE6 UOVA RUS",
      "quantita": 1,
      "prezzo": 1.5,
      "valuta": "EUR",
      "percentuale_sconto": null,
      "sconto_assoluto": null,
      "valore_scontato": null
    },
    {
      "nome": "NATURELLE2 UOVA RUS",
      "quantita": 1,
      "prezzo": 1.5,
      "valuta": "EUR",
      "percentuale_sconto": null,
      "sconto_assoluto": null,
      "valore_scontato": null
    },
    {
      "nome": "NATURELLE6 UOVA RUS",
      "quantita": 1,
      "prezzo": 1.5,
      "valuta": "EUR",
      "percentuale_sconto": null,
      "sconto_assoluto": null,
      "valore_scontato": null
    },
    {
      "nome": "PROC.S. COTTO A.Q.VIAlb",
      "quantita": 1,
      "prezzo": 2.08,
      "valuta": "EUR",
      "percentuale_sconto": null,
      "sconto_assoluto": null,
      "valore_scontato": null
    },
    {
      "nome": "GRANA PADANO GRATTUG",
      "quantita": 1,
      "prezzo": 1.59,
      "valuta": "EUR",
      "percentuale_sconto": null,
      "sconto_assoluto": null,
      "valore_scontato": null
    }
  ],
  "prezzo_totale": {
    "valore": 10.37,
    "valuta": "EUR"
  },
  "metodo_pagamento": "Carta Credito"
}